gdon/__init__.py
gdon/common.py
gdon/constants.py
gdon/diceware.py
gdon/generator.py
gdon/retrieve.py
gdon/transfer.py
gdon/utils.py
gdon/objects/Roboto-Medium.ttf
gdon/objects/recto.png
gdon/objects/verso.png
gdon/objects/wordlist.txt
gdon/silkaj/__init__.py
gdon/silkaj/auth.py
gdon/silkaj/blockchain_tools.py
gdon/silkaj/constants.py
gdon/silkaj/crypto_tools.py
gdon/silkaj/money.py
gdon/silkaj/network_tools.py
gdon/silkaj/tools.py
gdon/silkaj/tx.py
gdon/silkaj/tx_retrieve.py
gdon-0.1.0.data/scripts/gdon
gdon-0.1.0.dist-info/LICENSE.md
gdon-0.1.0.dist-info/METADATA
gdon-0.1.0.dist-info/WHEEL
gdon-0.1.0.dist-info/top_level.txt
gdon-0.1.0.dist-info/RECORD
