Metadata-Version: 2.1
Name: gdon
Version: 0.1.0
Summary: gdon helps creating paper tips for the Ğ1 libre crypto-currency ; and retrieve them after expiry.
Home-page: UNKNOWN
Author: matograine
Author-email: matograine@zaclys.net
License: UNKNOWN
Download-URL: https://git.duniter.org/matograine/g1pourboire/-/tags/0.0.9
Platform: UNKNOWN
Classifier: Programming Language :: Python :: 3
Classifier: License :: OSI Approved :: GNU Affero General Public License v3
Classifier: Development Status :: 3 - Alpha
Classifier: Operating System :: OS Independent
Classifier: Environment :: Console
Classifier: Intended Audience :: End Users/Desktop
Classifier: Natural Language :: French
Requires-Python: >=3.6
Requires-Dist: duniterpy (==0.58.1)
Requires-Dist: ipaddress
Requires-Dist: texttable
Requires-Dist: tabulate
Requires-Dist: pynacl
Requires-Dist: Pillow (>=6.0.0)
Requires-Dist: qrcode (>=6.1)
Requires-Dist: reportlab (>=3.5.23)
